webscrapper_client_api/__init__.py
webscrapper_client_api/async_client.py
webscrapper_client_api/client.py
webscrapper_client_api/exceptions.py
webscrapper_client_api-0.1.1.dist-info/METADATA
webscrapper_client_api-0.1.1.dist-info/WHEEL
webscrapper_client_api-0.1.1.dist-info/top_level.txt
webscrapper_client_api-0.1.1.dist-info/RECORD
