Metadata-Version: 2.4
Name: webscrapper-client-api
Version: 0.1.1
Summary: Async client for the webscrapper API
Author-email: pi11 <webii@pm.me>
License: WTFPL
Project-URL: Homepage, https://github.com/yourusername/webscrapper-client-api
Keywords: webscrapper,api,client,async,proxy,scraping
Classifier: Development Status :: 3 - Alpha
Classifier: Intended Audience :: Developers
Classifier: Programming Language :: Python :: 3
Classifier: Programming Language :: Python :: 3.7
Classifier: Programming Language :: Python :: 3.8
Classifier: Programming Language :: Python :: 3.9
Classifier: Programming Language :: Python :: 3.10
Classifier: Programming Language :: Python :: 3.11
Classifier: Topic :: Internet :: WWW/HTTP
Classifier: Topic :: Software Development :: Libraries :: Python Modules
Requires-Python: >=3.7
Requires-Dist: aiohttp>=3.7.0
